<?xml version="1.0" encoding="utf-8"?>
<form>
    <field
        name="catid"
        type="category"
        extension="com_content"
        label="COM_CONTENT_API_GRABBER_FIELD_CATID_LABEL"
        description="COM_CONTENT_API_GRABBER_FIELD_CATID_DESC"
        required="true"
    >
        <option value="">JOPTION_SELECT_CATEGORY</option>
    </field>

    <field
        name="created_by"
        type="user"
        label="COM_CONTENT_API_GRABBER_FIELD_CREATED_BY_LABEL"
        description="COM_CONTENT_API_GRABBER_FIELD_CREATED_BY_DESC"
    />

    <field
        name="state"
        type="list"
        label="COM_CONTENT_API_GRABBER_FIELD_STATE_LABEL"
        default="0"
    >
        <option value="1">JPUBLISHED</option>
        <option value="0">JUNPUBLISHED</option>
    </field>
</form>
